{
  "kind": "collectionType",
  "collectionName": "writers",
  "info": {
    "singularName": "writer",
    "pluralName": "writers",
    "displayName": "Blog Writer",
    "name": "writer",
    "description": ""
  },
  "options": {
    "increments": true,
    "timestamps": true,
    "draftAndPublish": false
  },
  "pluginOptions": {},
  "attributes": {
    "name": {
      "type": "string",
      "pluginOptions": {}
    },
    "picture": {
      "type": "media",
      "multiple": false,
      "required": false,
      "allowedTypes": [
        "images",
        "files",
        "videos"
      ],
      "pluginOptions": {}
    },
    "articles": {
      "type": "relation",
      "relation": "oneToMany",
      "target": "api::article.article",
      "mappedBy": "author"
    },
    "email": {
      "type": "string",
      "pluginOptions": {}
    }
  }
}
